setup.py
pyheartradio/__init__.py
pyheartradio.egg-info/PKG-INFO
pyheartradio.egg-info/SOURCES.txt
pyheartradio.egg-info/dependency_links.txt
pyheartradio.egg-info/requires.txt
pyheartradio.egg-info/top_level.txt