Metadata-Version: 2.1
Name: pyheartradio
Version: 0.0.1a1
Summary: search pyheartradio
Home-page: https://github.com/OpenJarbas/iheartradio
Author: JarbasAi
License: UNKNOWN
Platform: UNKNOWN
